claude_stream/__init__.py
claude_stream/__main__.py
claude_stream/blocks.py
claude_stream/cli.py
claude_stream/formatters.py
claude_stream/models.py
claude_stream/stream.py
claude_stream/watcher.py
claude_stream-0.1.1.dist-info/METADATA
claude_stream-0.1.1.dist-info/WHEEL
claude_stream-0.1.1.dist-info/entry_points.txt
claude_stream-0.1.1.dist-info/licenses/LICENSE
claude_stream-0.1.1.dist-info/RECORD
