Metadata-Version: 2.4
Name: claude-stream
Version: 0.1.1
Summary: Parse and prettify Claude Code JSONL stream output
Project-URL: Homepage, https://github.com/shitchell/claude-stream
Project-URL: Repository, https://github.com/shitchell/claude-stream
Project-URL: Issues, https://github.com/shitchell/claude-stream/issues
Author: Shaun Mitchell
License-Expression: WTFPL
License-File: LICENSE
Keywords: anthropic,claude,cli,jsonl,stream
Classifier: Development Status :: 4 - Beta
Classifier: Environment :: Console
Classifier: Intended Audience :: Developers
Classifier: License :: Public Domain
Classifier: Operating System :: OS Independent
Classifier: Programming Language :: Python :: 3
Classifier: Programming Language :: Python :: 3.10
Classifier: Programming Language :: Python :: 3.11
Classifier: Programming Language :: Python :: 3.12
Classifier: Topic :: Utilities
Requires-Python: >=3.10
Requires-Dist: pydantic>=2.0
Requires-Dist: typing-extensions>=4.0
Provides-Extra: watch
Requires-Dist: watchdog>=3.0; extra == 'watch'
